{"type":"furniture","name":"poster15","visualizationType":"furniture_static","logicType":"furniture_basic","spritesheet":{"meta":{"app":"FFConverter ~ Joopie","format":"RGBA8888","image":"poster15.png","scale":"1.0","size":{"w":64,"h":128},"version":"1.0"},"frames":{"poster15_poster15_icon_a.png":{"frame":{"x":2,"y":2,"w":23,"h":30},"sourceSize":{"w":23,"h":30},"spriteSourceSize":{"x":0,"y":0,"w":23,"h":30},"rotated":false,"trimmed":false},"poster15_poster15_64_a_4_0.png":{"frame":{"x":2,"y":34,"w":60,"h":82},"sourceSize":{"w":60,"h":82},"spriteSourceSize":{"x":0,"y":0,"w":60,"h":82},"rotated":false,"trimmed":false}}},"dimensions":{"x":1.875,"y":0.2,"z":1.7188},"directions":[90,180],"assets":{"poster15_64_a_2_0":{"source":"poster15_64_a_4_0","x":30,"y":41,"flipH":true},"poster15_64_a_4_0":{"x":30,"y":41},"poster15_icon_a":{"x":11,"y":15}},"visualizations":[{"layerCount":1,"angle":45,"size":64,"layers":{"0":{"z":-3000.0}},"directions":{"2":{},"4":{}}},{"layerCount":1,"angle":360,"size":1,"directions":{"0":{}}}]}