{"type":"furniture","name":"usva_firedragon","visualizationType":"furniture_animated","logicType":"furniture_multistate","spritesheet":"usva_firedragon_spritesheet.json","dimensions":{"x":1.0,"y":1.0,"z":0.0},"directions":[90,180],"assets":{"usva_firedragon_64_c_2_0":{"source":"usva_firedragon_64_c_4_0","x":20,"y":60,"flipH":true},"usva_firedragon_64_c_2_1":{"source":"usva_firedragon_64_c_4_1","x":8,"y":69,"flipH":true},"usva_firedragon_64_c_4_0":{"x":20,"y":60},"usva_firedragon_64_c_4_1":{"x":8,"y":69},"usva_firedragon_64_d_2_0":{"source":"usva_firedragon_64_d_4_0","x":17,"y":34,"flipH":true},"usva_firedragon_64_d_4_0":{"x":17,"y":34},"usva_firedragon_icon_b":{"x":9,"y":15},"usva_firedragon_icon_a":{"x":13,"y":15},"usva_firedragon_64_f_4_3":{"x":7,"y":94},"usva_firedragon_64_f_4_4":{"x":8,"y":95},"usva_firedragon_64_f_2_3":{"source":"usva_firedragon_64_f_4_3","x":7,"y":94,"flipH":true},"usva_firedragon_64_f_4_1":{"x":3,"y":96},"usva_firedragon_64_f_2_4":{"source":"usva_firedragon_64_f_4_4","x":8,"y":95,"flipH":true},"usva_firedragon_64_f_4_2":{"x":5,"y":91},"usva_firedragon_64_f_2_1":{"source":"usva_firedragon_64_f_4_1","x":3,"y":96,"flipH":true},"usva_firedragon_64_f_2_2":{"source":"usva_firedragon_64_f_4_2","x":5,"y":91,"flipH":true},"usva_firedragon_64_f_4_0":{"x":28,"y":-2},"usva_firedragon_64_f_2_0":{"source":"usva_firedragon_64_f_4_0","x":28,"y":-2,"flipH":true},"usva_firedragon_64_e_2_0":{"source":"usva_firedragon_64_e_4_0","x":19,"y":59,"flipH":true},"usva_firedragon_64_e_2_1":{"source":"usva_firedragon_64_e_4_1","x":7,"y":68,"flipH":true},"usva_firedragon_64_e_4_0":{"x":19,"y":59},"usva_firedragon_64_e_4_1":{"x":7,"y":68},"usva_firedragon_64_a_2_0":{"source":"usva_firedragon_64_a_4_0","x":28,"y":13,"flipH":true},"usva_firedragon_64_a_4_0":{"x":28,"y":13},"usva_firedragon_64_g_4_0":{"source":"usva_firedragon_64_f_4_0","x":28,"y":-2},"usva_firedragon_64_b_4_0":{"x":18,"y":35},"usva_firedragon_64_g_4_1":{"x":25,"y":114},"usva_firedragon_64_b_2_0":{"source":"usva_firedragon_64_b_4_0","x":18,"y":35,"flipH":true},"usva_firedragon_64_g_2_0":{"source":"usva_firedragon_64_f_4_0","x":28,"y":-2,"flipH":true},"usva_firedragon_64_g_2_1":{"source":"usva_firedragon_64_g_4_1","x":25,"y":114,"flipH":true},"usva_firedragon_64_sd_4_0":{"x":29,"y":3},"usva_firedragon_64_sd_2_0":{"source":"usva_firedragon_64_sd_4_0","x":29,"y":3,"flipH":true}},"visualization":{"layerCount":7,"angle":45,"layers":{"3":{"ink":"ADD"},"4":{"ink":"ADD"},"5":{"alpha":204},"6":{"ink":"ADD","ignoreMouse":true}},"directions":{"2":{},"4":{}},"colors":{"0":{"layers":{"1":{"color":16777215},"2":{"color":16777215}}},"1":{"layers":{"1":{"color":16777215},"2":{"color":16777215}}},"2":{"layers":{"1":{"color":16777215},"2":{"color":16777215}}},"4":{"layers":{"1":{"color":16777215},"2":{"color":16777215}}},"5":{"layers":{"1":{"color":16777215},"2":{"color":16777215}}},"6":{"layers":{"1":{"color":16777215},"2":{"color":16777215}}},"7":{"layers":{"1":{"color":16777215},"2":{"color":16777215}}},"8":{"layers":{"1":{"color":16777215},"2":{"color":16777215}}},"9":{"layers":{"1":{"color":16777215},"2":{"color":16777215}}}},"iconColors":{"0":{"layers":{"1":{"color":16777215}}},"1":{"layers":{"1":{"color":16777215}}},"2":{"layers":{"1":{"color":16777215}}},"4":{"layers":{"1":{"color":16777215}}},"5":{"layers":{"1":{"color":16777215}}},"6":{"layers":{"1":{"color":16777215}}},"7":{"layers":{"1":{"color":16777215}}},"8":{"layers":{"1":{"color":16777215}}},"9":{"layers":{"1":{"color":16777215}}}},"animations":{"0":{"layers":{"0":{"frameSequences":{"0":{"frames":{"0":{"id":0}}}}},"1":{"frameSequences":{"0":{"frames":{"0":{"id":0}}}}},"2":{"frameSequences":{"0":{"frames":{"0":{"id":0}}}}},"3":{"frameSequences":{"0":{"frames":{"0":{"id":0}}}}},"4":{"frameSequences":{"0":{"frames":{"0":{"id":0}}}}},"5":{"frameSequences":{"0":{"frames":{"0":{"id":0}}}}},"6":{"frameSequences":{"0":{"frames":{"0":{"id":0}}}}}}},"1":{"layers":{"2":{"frameSequences":{"0":{"frames":{"0":{"id":1}}}}},"4":{"frameSequences":{"0":{"frames":{"0":{"id":1}}}}},"5":{"loopCount":0,"frameRepeat":2,"frameSequences":{"0":{"frames":{"0":{"id":1},"1":{"id":2},"2":{"id":3},"3":{"id":4}}}}},"6":{"frameSequences":{"0":{"frames":{"0":{"id":1}}}}}}}}}}