{"meta":{"app":"FFConverter ~ Joopie","format":"RGBA8888","image":"ete_sol.png","scale":"1.0","size":{"w":1024,"h":64},"version":"1.0"},"frames":{"ete_sol_ete_sol_64_a_2_4.png":{"frame":{"x":218,"y":2,"w":106,"h":54},"sourceSize":{"w":106,"h":54},"spriteSourceSize":{"x":0,"y":0,"w":106,"h":54},"rotated":false,"trimmed":false},"ete_sol_ete_sol_64_a_2_5.png":{"frame":{"x":434,"y":2,"w":106,"h":54},"sourceSize":{"w":106,"h":54},"spriteSourceSize":{"x":0,"y":0,"w":106,"h":54},"rotated":false,"trimmed":false},"ete_sol_ete_sol_64_a_2_2.png":{"frame":{"x":542,"y":2,"w":106,"h":54},"sourceSize":{"w":106,"h":54},"spriteSourceSize":{"x":0,"y":0,"w":106,"h":54},"rotated":false,"trimmed":false},"ete_sol_ete_sol_64_a_2_3.png":{"frame":{"x":650,"y":2,"w":106,"h":54},"sourceSize":{"w":106,"h":54},"spriteSourceSize":{"x":0,"y":0,"w":106,"h":54},"rotated":false,"trimmed":false},"ete_sol_ete_sol_64_a_2_1.png":{"frame":{"x":758,"y":2,"w":106,"h":54},"sourceSize":{"w":106,"h":54},"spriteSourceSize":{"x":0,"y":0,"w":106,"h":54},"rotated":false,"trimmed":false},"ete_sol_ete_sol_64_a_2_6.png":{"frame":{"x":2,"y":2,"w":106,"h":54},"sourceSize":{"w":106,"h":54},"spriteSourceSize":{"x":0,"y":0,"w":106,"h":54},"rotated":false,"trimmed":false},"ete_sol_ete_sol_64_a_2_7.png":{"frame":{"x":110,"y":2,"w":106,"h":54},"sourceSize":{"w":106,"h":54},"spriteSourceSize":{"x":0,"y":0,"w":106,"h":54},"rotated":false,"trimmed":false},"ete_sol_ete_sol_icon_a.png":{"frame":{"x":326,"y":2,"w":106,"h":54},"sourceSize":{"w":106,"h":54},"spriteSourceSize":{"x":0,"y":0,"w":106,"h":54},"rotated":false,"trimmed":false}}}