{"meta":{"app":"Holo5-Excavator ~ Holo5 (github:Pi-Bouf)","format":"RGBA8888","image":"atlantis17_statue.png","scale":"1.0","size":{"w":181,"h":193},"version":"1.0"},"frames":{"atlantis17_statue_atlantis17_statue_64_a_2_0":{"frame":{"x":0,"y":0,"w":68,"h":193},"sourceSize":{"w":68,"h":193},"spriteSourceSize":{"x":-33,"y":-177,"w":68,"h":193},"rotated":false,"trimmed":true},"atlantis17_statue_atlantis17_statue_64_a_4_0":{"frame":{"x":68,"y":0,"w":68,"h":193},"sourceSize":{"w":68,"h":193},"spriteSourceSize":{"x":-33,"y":-177,"w":68,"h":193},"rotated":false,"trimmed":true},"atlantis17_statue_atlantis17_statue_32_a_2_0":{"frame":{"x":136,"y":0,"w":34,"h":96},"sourceSize":{"w":34,"h":96},"spriteSourceSize":{"x":-17,"y":-88,"w":34,"h":96},"rotated":false,"trimmed":true},"atlantis17_statue_atlantis17_statue_32_a_4_0":{"frame":{"x":136,"y":96,"w":34,"h":96},"sourceSize":{"w":34,"h":96},"spriteSourceSize":{"x":-17,"y":-88,"w":34,"h":96},"rotated":false,"trimmed":true},"atlantis17_statue_atlantis17_statue_icon_a":{"frame":{"x":170,"y":0,"w":11,"h":30},"sourceSize":{"w":11,"h":30},"spriteSourceSize":{"x":-8,"y":-14,"w":11,"h":30},"rotated":false,"trimmed":true}},"furniProperty":{"infos":{"logic":"furniture_multistate","visualization":"furniture_animated"},"dimensions":{"x":1,"y":1,"z":"0.01"},"visualization":{"layerCount":1,"layers":{},"directions":[2,4],"colors":{},"animation":{}}}}