{"meta":{"app":"Holo5-Excavator ~ Holo5 (github:Pi-Bouf)","format":"RGBA8888","image":"pokeweebzs520.png","scale":"1.0","size":{"w":1008,"h":794},"version":"1.0"},"frames":{"pokeweebzs520_pokeweebzs520_64_a_2_1":{"frame":{"x":0,"y":0,"w":144,"h":124},"sourceSize":{"w":144,"h":124},"spriteSourceSize":{"x":-72,"y":-118,"w":144,"h":124},"rotated":false,"trimmed":true},"pokeweebzs520_pokeweebzs520_64_a_2_10":{"frame":{"x":144,"y":0,"w":144,"h":124},"sourceSize":{"w":144,"h":124},"spriteSourceSize":{"x":-72,"y":-118,"w":144,"h":124},"rotated":false,"trimmed":true},"pokeweebzs520_pokeweebzs520_64_a_2_11":{"frame":{"x":0,"y":124,"w":144,"h":124},"sourceSize":{"w":144,"h":124},"spriteSourceSize":{"x":-72,"y":-118,"w":144,"h":124},"rotated":false,"trimmed":true},"pokeweebzs520_pokeweebzs520_64_a_2_12":{"frame":{"x":144,"y":124,"w":144,"h":124},"sourceSize":{"w":144,"h":124},"spriteSourceSize":{"x":-72,"y":-118,"w":144,"h":124},"rotated":false,"trimmed":true},"pokeweebzs520_pokeweebzs520_64_a_2_13":{"frame":{"x":288,"y":0,"w":144,"h":124},"sourceSize":{"w":144,"h":124},"spriteSourceSize":{"x":-72,"y":-118,"w":144,"h":124},"rotated":false,"trimmed":true},"pokeweebzs520_pokeweebzs520_64_a_2_14":{"frame":{"x":288,"y":124,"w":144,"h":124},"sourceSize":{"w":144,"h":124},"spriteSourceSize":{"x":-72,"y":-118,"w":144,"h":124},"rotated":false,"trimmed":true},"pokeweebzs520_pokeweebzs520_64_a_2_15":{"frame":{"x":0,"y":248,"w":144,"h":124},"sourceSize":{"w":144,"h":124},"spriteSourceSize":{"x":-72,"y":-118,"w":144,"h":124},"rotated":false,"trimmed":true},"pokeweebzs520_pokeweebzs520_64_a_2_16":{"frame":{"x":144,"y":248,"w":144,"h":124},"sourceSize":{"w":144,"h":124},"spriteSourceSize":{"x":-72,"y":-118,"w":144,"h":124},"rotated":false,"trimmed":true},"pokeweebzs520_pokeweebzs520_64_a_2_17":{"frame":{"x":288,"y":248,"w":144,"h":124},"sourceSize":{"w":144,"h":124},"spriteSourceSize":{"x":-72,"y":-118,"w":144,"h":124},"rotated":false,"trimmed":true},"pokeweebzs520_pokeweebzs520_64_a_2_18":{"frame":{"x":432,"y":0,"w":144,"h":124},"sourceSize":{"w":144,"h":124},"spriteSourceSize":{"x":-72,"y":-118,"w":144,"h":124},"rotated":false,"trimmed":true},"pokeweebzs520_pokeweebzs520_64_a_2_19":{"frame":{"x":432,"y":124,"w":144,"h":124},"sourceSize":{"w":144,"h":124},"spriteSourceSize":{"x":-72,"y":-118,"w":144,"h":124},"rotated":false,"trimmed":true},"pokeweebzs520_pokeweebzs520_64_a_2_2":{"frame":{"x":432,"y":248,"w":144,"h":124},"sourceSize":{"w":144,"h":124},"spriteSourceSize":{"x":-72,"y":-118,"w":144,"h":124},"rotated":false,"trimmed":true},"pokeweebzs520_pokeweebzs520_64_a_2_20":{"frame":{"x":0,"y":372,"w":144,"h":124},"sourceSize":{"w":144,"h":124},"spriteSourceSize":{"x":-72,"y":-118,"w":144,"h":124},"rotated":false,"trimmed":true},"pokeweebzs520_pokeweebzs520_64_a_2_21":{"frame":{"x":144,"y":372,"w":144,"h":124},"sourceSize":{"w":144,"h":124},"spriteSourceSize":{"x":-72,"y":-118,"w":144,"h":124},"rotated":false,"trimmed":true},"pokeweebzs520_pokeweebzs520_64_a_2_3":{"frame":{"x":288,"y":372,"w":144,"h":124},"sourceSize":{"w":144,"h":124},"spriteSourceSize":{"x":-72,"y":-118,"w":144,"h":124},"rotated":false,"trimmed":true},"pokeweebzs520_pokeweebzs520_64_a_2_4":{"frame":{"x":432,"y":372,"w":144,"h":124},"sourceSize":{"w":144,"h":124},"spriteSourceSize":{"x":-72,"y":-118,"w":144,"h":124},"rotated":false,"trimmed":true},"pokeweebzs520_pokeweebzs520_64_a_2_5":{"frame":{"x":576,"y":0,"w":144,"h":124},"sourceSize":{"w":144,"h":124},"spriteSourceSize":{"x":-72,"y":-118,"w":144,"h":124},"rotated":false,"trimmed":true},"pokeweebzs520_pokeweebzs520_64_a_2_6":{"frame":{"x":576,"y":124,"w":144,"h":124},"sourceSize":{"w":144,"h":124},"spriteSourceSize":{"x":-72,"y":-118,"w":144,"h":124},"rotated":false,"trimmed":true},"pokeweebzs520_pokeweebzs520_64_a_2_7":{"frame":{"x":576,"y":248,"w":144,"h":124},"sourceSize":{"w":144,"h":124},"spriteSourceSize":{"x":-72,"y":-118,"w":144,"h":124},"rotated":false,"trimmed":true},"pokeweebzs520_pokeweebzs520_64_a_2_8":{"frame":{"x":576,"y":372,"w":144,"h":124},"sourceSize":{"w":144,"h":124},"spriteSourceSize":{"x":-72,"y":-118,"w":144,"h":124},"rotated":false,"trimmed":true},"pokeweebzs520_pokeweebzs520_64_a_2_9":{"frame":{"x":0,"y":496,"w":144,"h":124},"sourceSize":{"w":144,"h":124},"spriteSourceSize":{"x":-72,"y":-118,"w":144,"h":124},"rotated":false,"trimmed":true},"pokeweebzs520_pokeweebzs520_64_a_4_1":{"frame":{"x":144,"y":496,"w":144,"h":124},"sourceSize":{"w":144,"h":124},"spriteSourceSize":{"x":-72,"y":-118,"w":144,"h":124},"rotated":false,"trimmed":true},"pokeweebzs520_pokeweebzs520_64_a_4_10":{"frame":{"x":288,"y":496,"w":144,"h":124},"sourceSize":{"w":144,"h":124},"spriteSourceSize":{"x":-72,"y":-118,"w":144,"h":124},"rotated":false,"trimmed":true},"pokeweebzs520_pokeweebzs520_64_a_4_11":{"frame":{"x":432,"y":496,"w":144,"h":124},"sourceSize":{"w":144,"h":124},"spriteSourceSize":{"x":-72,"y":-118,"w":144,"h":124},"rotated":false,"trimmed":true},"pokeweebzs520_pokeweebzs520_64_a_4_12":{"frame":{"x":576,"y":496,"w":144,"h":124},"sourceSize":{"w":144,"h":124},"spriteSourceSize":{"x":-72,"y":-118,"w":144,"h":124},"rotated":false,"trimmed":true},"pokeweebzs520_pokeweebzs520_64_a_4_13":{"frame":{"x":720,"y":0,"w":144,"h":124},"sourceSize":{"w":144,"h":124},"spriteSourceSize":{"x":-72,"y":-118,"w":144,"h":124},"rotated":false,"trimmed":true},"pokeweebzs520_pokeweebzs520_64_a_4_14":{"frame":{"x":720,"y":124,"w":144,"h":124},"sourceSize":{"w":144,"h":124},"spriteSourceSize":{"x":-72,"y":-118,"w":144,"h":124},"rotated":false,"trimmed":true},"pokeweebzs520_pokeweebzs520_64_a_4_15":{"frame":{"x":720,"y":248,"w":144,"h":124},"sourceSize":{"w":144,"h":124},"spriteSourceSize":{"x":-72,"y":-118,"w":144,"h":124},"rotated":false,"trimmed":true},"pokeweebzs520_pokeweebzs520_64_a_4_16":{"frame":{"x":720,"y":372,"w":144,"h":124},"sourceSize":{"w":144,"h":124},"spriteSourceSize":{"x":-72,"y":-118,"w":144,"h":124},"rotated":false,"trimmed":true},"pokeweebzs520_pokeweebzs520_64_a_4_17":{"frame":{"x":720,"y":496,"w":144,"h":124},"sourceSize":{"w":144,"h":124},"spriteSourceSize":{"x":-72,"y":-118,"w":144,"h":124},"rotated":false,"trimmed":true},"pokeweebzs520_pokeweebzs520_64_a_4_18":{"frame":{"x":0,"y":620,"w":144,"h":124},"sourceSize":{"w":144,"h":124},"spriteSourceSize":{"x":-72,"y":-118,"w":144,"h":124},"rotated":false,"trimmed":true},"pokeweebzs520_pokeweebzs520_64_a_4_19":{"frame":{"x":144,"y":620,"w":144,"h":124},"sourceSize":{"w":144,"h":124},"spriteSourceSize":{"x":-72,"y":-118,"w":144,"h":124},"rotated":false,"trimmed":true},"pokeweebzs520_pokeweebzs520_64_a_4_2":{"frame":{"x":288,"y":620,"w":144,"h":124},"sourceSize":{"w":144,"h":124},"spriteSourceSize":{"x":-72,"y":-118,"w":144,"h":124},"rotated":false,"trimmed":true},"pokeweebzs520_pokeweebzs520_64_a_4_20":{"frame":{"x":432,"y":620,"w":144,"h":124},"sourceSize":{"w":144,"h":124},"spriteSourceSize":{"x":-72,"y":-118,"w":144,"h":124},"rotated":false,"trimmed":true},"pokeweebzs520_pokeweebzs520_64_a_4_21":{"frame":{"x":576,"y":620,"w":144,"h":124},"sourceSize":{"w":144,"h":124},"spriteSourceSize":{"x":-72,"y":-118,"w":144,"h":124},"rotated":false,"trimmed":true},"pokeweebzs520_pokeweebzs520_64_a_4_3":{"frame":{"x":720,"y":620,"w":144,"h":124},"sourceSize":{"w":144,"h":124},"spriteSourceSize":{"x":-72,"y":-118,"w":144,"h":124},"rotated":false,"trimmed":true},"pokeweebzs520_pokeweebzs520_64_a_4_4":{"frame":{"x":864,"y":0,"w":144,"h":124},"sourceSize":{"w":144,"h":124},"spriteSourceSize":{"x":-72,"y":-118,"w":144,"h":124},"rotated":false,"trimmed":true},"pokeweebzs520_pokeweebzs520_64_a_4_5":{"frame":{"x":864,"y":124,"w":144,"h":124},"sourceSize":{"w":144,"h":124},"spriteSourceSize":{"x":-72,"y":-118,"w":144,"h":124},"rotated":false,"trimmed":true},"pokeweebzs520_pokeweebzs520_64_a_4_6":{"frame":{"x":864,"y":248,"w":144,"h":124},"sourceSize":{"w":144,"h":124},"spriteSourceSize":{"x":-72,"y":-118,"w":144,"h":124},"rotated":false,"trimmed":true},"pokeweebzs520_pokeweebzs520_64_a_4_7":{"frame":{"x":864,"y":372,"w":144,"h":124},"sourceSize":{"w":144,"h":124},"spriteSourceSize":{"x":-72,"y":-118,"w":144,"h":124},"rotated":false,"trimmed":true},"pokeweebzs520_pokeweebzs520_64_a_4_8":{"frame":{"x":864,"y":496,"w":144,"h":124},"sourceSize":{"w":144,"h":124},"spriteSourceSize":{"x":-72,"y":-118,"w":144,"h":124},"rotated":false,"trimmed":true},"pokeweebzs520_pokeweebzs520_64_a_4_9":{"frame":{"x":864,"y":620,"w":144,"h":124},"sourceSize":{"w":144,"h":124},"spriteSourceSize":{"x":-72,"y":-118,"w":144,"h":124},"rotated":false,"trimmed":true},"pokeweebzs520_pokeweebzs520_64_a_2_0":{"frame":{"x":0,"y":744,"w":48,"h":50},"sourceSize":{"w":48,"h":50},"spriteSourceSize":{"x":-24,"y":-42,"w":48,"h":50},"rotated":false,"trimmed":true},"pokeweebzs520_pokeweebzs520_64_a_4_0":{"frame":{"x":48,"y":744,"w":48,"h":50},"sourceSize":{"w":48,"h":50},"spriteSourceSize":{"x":-24,"y":-42,"w":48,"h":50},"rotated":false,"trimmed":true},"pokeweebzs520_pokeweebzs520_icon_a":{"frame":{"x":96,"y":744,"w":32,"h":32},"sourceSize":{"w":32,"h":32},"spriteSourceSize":{"x":-10,"y":-10,"w":32,"h":32},"rotated":false,"trimmed":true},"pokeweebzs520_pokeweebzs520_64_sd_2_0":{"frame":{"x":128,"y":744,"w":34,"h":17},"sourceSize":{"w":34,"h":17},"spriteSourceSize":{"x":-17,"y":-8,"w":34,"h":17},"rotated":false,"trimmed":true},"pokeweebzs520_pokeweebzs520_64_sd_4_0":{"frame":{"x":162,"y":744,"w":34,"h":17},"sourceSize":{"w":34,"h":17},"spriteSourceSize":{"x":-17,"y":-8,"w":34,"h":17},"rotated":false,"trimmed":true}},"furniProperty":{"infos":{"logic":"furniture_multistate","visualization":"furniture_animated"},"dimensions":{"x":1,"y":1,"z":"1.0"},"visualization":{"layerCount":1,"layers":{"0":{"id":0,"ignoreMouse":false}},"directions":[2,4],"colors":{},"animation":{"0":{"0":{"frameSequence":[1]}},"1":{"0":{"frameSequence":[1,2,3,4,5,6,7,8,9,10,11,12,13,14,15,16,17,18,19,20,21],"loopCount":0,"frameRepeat":1}},"2":{"0":{"frameSequence":[0]}}}}}}