{"meta":{"app":"FFConverter ~ Joopie","format":"RGBA8888","image":"hat_U_bunniehat.png","scale":"1.0","size":{"w":512,"h":64},"version":"1.0"},"frames":{"hat_U_bunniehat_h_std_ha_3131_3_0.png":{"frame":{"x":320,"y":4,"w":15,"h":23},"sourceSize":{"w":15,"h":23},"spriteSourceSize":{"x":0,"y":0,"w":15,"h":23},"rotated":false,"trimmed":false},"hat_U_bunniehat_h_lay_ha_3113_2_0.png":{"frame":{"x":219,"y":31,"w":38,"h":31},"sourceSize":{"w":38,"h":31},"spriteSourceSize":{"x":0,"y":0,"w":38,"h":31},"rotated":false,"trimmed":false},"hat_U_bunniehat_h_spk_ha_3131_1_0.png":{"frame":{"x":384,"y":15,"w":9,"h":24},"sourceSize":{"w":9,"h":24},"spriteSourceSize":{"x":0,"y":0,"w":9,"h":24},"rotated":false,"trimmed":false},"hat_U_bunniehat_h_std_ha_3132_1_0.png":{"frame":{"x":66,"y":28,"w":38,"h":34},"sourceSize":{"w":38,"h":34},"spriteSourceSize":{"x":0,"y":0,"w":38,"h":34},"rotated":false,"trimmed":false},"hat_U_bunniehat_h_spk_ha_3113_1_0.png":{"frame":{"x":354,"y":41,"w":38,"h":21},"sourceSize":{"w":38,"h":21},"spriteSourceSize":{"x":0,"y":0,"w":38,"h":21},"rotated":false,"trimmed":false},"hat_U_bunniehat_h_std_ha_3131_1_0.png":{"frame":{"x":309,"y":3,"w":9,"h":25},"sourceSize":{"w":9,"h":25},"spriteSourceSize":{"x":0,"y":0,"w":9,"h":25},"rotated":false,"trimmed":false},"hat_U_bunniehat_h_std_ha_3113_2_0.png":{"frame":{"x":66,"y":2,"w":34,"h":24},"sourceSize":{"w":34,"h":24},"spriteSourceSize":{"x":0,"y":0,"w":34,"h":24},"rotated":false,"trimmed":false},"hat_U_bunniehat_h_lay_ha_3132_2_0.png":{"frame":{"x":2,"y":17,"w":30,"h":45},"sourceSize":{"w":30,"h":45},"spriteSourceSize":{"x":0,"y":0,"w":30,"h":45},"rotated":false,"trimmed":false},"hat_U_bunniehat_h_spk_ha_3132_2_0.png":{"frame":{"x":182,"y":26,"w":35,"h":36},"sourceSize":{"w":35,"h":36},"spriteSourceSize":{"x":0,"y":0,"w":35,"h":36},"rotated":false,"trimmed":false},"hat_U_bunniehat_h_lay_ha_3131_2_0.png":{"frame":{"x":183,"y":3,"w":22,"h":21},"sourceSize":{"w":22,"h":21},"spriteSourceSize":{"x":0,"y":0,"w":22,"h":21},"rotated":false,"trimmed":false},"hat_U_bunniehat_h_std_ha_3113_3_0.png":{"frame":{"x":292,"y":30,"w":30,"h":32},"sourceSize":{"w":30,"h":32},"spriteSourceSize":{"x":0,"y":0,"w":30,"h":32},"rotated":false,"trimmed":false},"hat_U_bunniehat_h_lsp_ha_3131_2_0.png":{"frame":{"x":159,"y":3,"w":22,"h":21},"sourceSize":{"w":22,"h":21},"spriteSourceSize":{"x":0,"y":0,"w":22,"h":21},"rotated":false,"trimmed":false},"hat_U_bunniehat_h_spk_ha_3132_7_0.png":{"frame":{"x":324,"y":29,"w":28,"h":33},"sourceSize":{"w":28,"h":33},"spriteSourceSize":{"x":0,"y":0,"w":28,"h":33},"rotated":false,"trimmed":false},"hat_U_bunniehat_h_spk_ha_3113_7_0.png":{"frame":{"x":429,"y":42,"w":30,"h":20},"sourceSize":{"w":30,"h":20},"spriteSourceSize":{"x":0,"y":0,"w":30,"h":20},"rotated":false,"trimmed":false},"hat_U_bunniehat_h_lsp_ha_3132_2_0.png":{"frame":{"x":34,"y":17,"w":30,"h":45},"sourceSize":{"w":30,"h":45},"spriteSourceSize":{"x":0,"y":0,"w":30,"h":45},"rotated":false,"trimmed":false},"hat_U_bunniehat_h_std_ha_3132_3_0.png":{"frame":{"x":461,"y":34,"w":28,"h":28},"sourceSize":{"w":28,"h":28},"spriteSourceSize":{"x":0,"y":0,"w":28,"h":28},"rotated":false,"trimmed":false},"hat_U_bunniehat_h_std_ha_3113_0_0.png":{"frame":{"x":394,"y":42,"w":33,"h":20},"sourceSize":{"w":33,"h":20},"spriteSourceSize":{"x":0,"y":0,"w":33,"h":20},"rotated":false,"trimmed":false},"hat_U_bunniehat_h_spk_ha_3131_2_0.png":{"frame":{"x":292,"y":2,"w":15,"h":26},"sourceSize":{"w":15,"h":26},"spriteSourceSize":{"x":0,"y":0,"w":15,"h":26},"rotated":false,"trimmed":false},"hat_U_bunniehat_h_std_ha_3132_2_0.png":{"frame":{"x":145,"y":26,"w":35,"h":36},"sourceSize":{"w":35,"h":36},"spriteSourceSize":{"x":0,"y":0,"w":35,"h":36},"rotated":false,"trimmed":false},"hat_U_bunniehat_h_std_ha_3131_2_0.png":{"frame":{"x":491,"y":35,"w":15,"h":27},"sourceSize":{"w":15,"h":27},"spriteSourceSize":{"x":0,"y":0,"w":15,"h":27},"rotated":false,"trimmed":false},"hat_U_bunniehat_h_std_ha_3113_1_0.png":{"frame":{"x":102,"y":5,"w":38,"h":21},"sourceSize":{"w":38,"h":21},"spriteSourceSize":{"x":0,"y":0,"w":38,"h":21},"rotated":false,"trimmed":false},"hat_U_bunniehat_h_spk_ha_3132_3_0.png":{"frame":{"x":354,"y":11,"w":28,"h":28},"sourceSize":{"w":28,"h":28},"spriteSourceSize":{"x":0,"y":0,"w":28,"h":28},"rotated":false,"trimmed":false},"hat_U_bunniehat_h_std_ha_3132_0_0.png":{"frame":{"x":259,"y":22,"w":31,"h":40},"sourceSize":{"w":31,"h":40},"spriteSourceSize":{"x":0,"y":0,"w":31,"h":40},"rotated":false,"trimmed":false},"hat_U_bunniehat_h_spk_ha_3131_3_0.png":{"frame":{"x":142,"y":2,"w":15,"h":22},"sourceSize":{"w":15,"h":22},"spriteSourceSize":{"x":0,"y":0,"w":15,"h":22},"rotated":false,"trimmed":false},"hat_U_bunniehat_h_spk_ha_3132_1_0.png":{"frame":{"x":106,"y":28,"w":37,"h":34},"sourceSize":{"w":37,"h":34},"spriteSourceSize":{"x":0,"y":0,"w":37,"h":34},"rotated":false,"trimmed":false}}}