{"type":"hr","name":"hair_U_showe3","spritesheet":"hair_U_showe3_spritesheet.json","assets":{"h_std_hr_7538_0_0":{"x":-10,"y":93},"h_std_hrb_7538_0_0":{"x":-10,"y":93},"h_spk_hrb_7538_7_0":{"x":-10,"y":96},"h_lay_hrb_7538_2_0":{"x":24,"y":39},"h_lay_hr_7538_2_0":{"x":24,"y":39},"h_spk_hrb_7538_1_0":{"x":-10,"y":96},"h_std_hr_7538_3_0":{"x":-10,"y":96},"h_spk_hrb_7538_0_0":{"x":-10,"y":94},"h_std_hr_7538_2_0":{"x":-10,"y":95},"h_spk_hrb_7538_3_0":{"x":-10,"y":97},"h_std_hr_7538_1_0":{"x":-10,"y":95},"h_spk_hrb_7538_2_0":{"x":-10,"y":96},"h_std_hr_7538_7_0":{"x":-10,"y":95},"h_spk_hr_7538_1_0":{"x":-10,"y":96},"h_spk_hr_7538_0_0":{"x":-10,"y":94},"h_spk_hr_7538_3_0":{"x":-10,"y":97},"h_spk_hr_7538_2_0":{"x":-10,"y":96},"h_std_hrb_7538_3_0":{"x":-10,"y":96},"h_spk_hr_7538_7_0":{"x":-10,"y":96},"h_std_hrb_7538_1_0":{"x":-10,"y":95},"h_std_hrb_7538_2_0":{"x":-10,"y":95},"h_std_hrb_7538_7_0":{"x":-10,"y":95}}}