{"type":"furniture","name":"art_c20_plant","visualizationType":"furniture_static","logicType":"furniture_basic","spritesheet":{"meta":{"app":"FFConverter ~ Joopie","format":"RGBA8888","image":"art_c20_plant.png","scale":"1.0","size":{"w":64,"h":128},"version":"1.0"},"frames":{"art_c20_plant_art_c20_plant_icon_a.png":{"frame":{"x":2,"y":2,"w":20,"h":30},"sourceSize":{"w":20,"h":30},"spriteSourceSize":{"x":0,"y":0,"w":20,"h":30},"rotated":false,"trimmed":false},"art_c20_plant_art_c20_plant_64_a_0_0.png":{"frame":{"x":2,"y":34,"w":48,"h":85},"sourceSize":{"w":48,"h":85},"spriteSourceSize":{"x":0,"y":0,"w":48,"h":85},"rotated":false,"trimmed":false},"art_c20_plant_art_c20_plant_64_sd_0_0.png":{"frame":{"x":24,"y":18,"w":26,"h":14},"sourceSize":{"w":26,"h":14},"spriteSourceSize":{"x":0,"y":0,"w":26,"h":14},"rotated":false,"trimmed":false}}},"dimensions":{"x":1.0,"y":1.0,"z":1.0},"directions":[0,90],"assets":{"art_c20_plant_64_sd_0_0":{"x":13,"y":5},"art_c20_plant_icon_a":{"x":8,"y":14},"art_c20_plant_64_a_0_0":{"x":23,"y":77},"art_c20_plant_64_a_2_0":{"source":"art_c20_plant_64_a_0_0","x":23,"y":77,"flipH":true},"art_c20_plant_64_sd_2_0":{"source":"art_c20_plant_64_sd_0_0","x":13,"y":5,"flipH":true}},"visualizations":[{"layerCount":1,"angle":360,"size":1},{"layerCount":1,"angle":45,"size":64,"directions":{"0":{},"2":{}}}]}