{"meta":{"app":"FFConverter ~ Joopie","format":"RGBA8888","image":"birds_r18_puffin.png","scale":"1.0","size":{"w":256,"h":256},"version":"1.0"},"frames":{"birds_r18_puffin_birds_r18_puffin_64_d_0_18.png":{"frame":{"x":154,"y":173,"w":30,"h":40},"sourceSize":{"w":30,"h":40},"spriteSourceSize":{"x":0,"y":0,"w":30,"h":40},"rotated":false,"trimmed":false},"birds_r18_puffin_birds_r18_puffin_64_a_0_1.png":{"frame":{"x":96,"y":3,"w":30,"h":15},"sourceSize":{"w":30,"h":15},"spriteSourceSize":{"x":0,"y":0,"w":30,"h":15},"rotated":false,"trimmed":false},"birds_r18_puffin_birds_r18_puffin_64_c_0_1.png":{"frame":{"x":62,"y":79,"w":28,"h":42},"sourceSize":{"w":28,"h":42},"spriteSourceSize":{"x":0,"y":0,"w":28,"h":42},"rotated":false,"trimmed":false},"birds_r18_puffin_birds_r18_puffin_64_c_0_12.png":{"frame":{"x":145,"y":215,"w":31,"h":39},"sourceSize":{"w":31,"h":39},"spriteSourceSize":{"x":0,"y":0,"w":31,"h":39},"rotated":false,"trimmed":false},"birds_r18_puffin_birds_r18_puffin_64_c_0_11.png":{"frame":{"x":160,"y":32,"w":30,"h":31},"sourceSize":{"w":30,"h":31},"spriteSourceSize":{"x":0,"y":0,"w":30,"h":31},"rotated":false,"trimmed":false},"birds_r18_puffin_birds_r18_puffin_64_d_0_5.png":{"frame":{"x":2,"y":32,"w":28,"h":44},"sourceSize":{"w":28,"h":44},"spriteSourceSize":{"x":0,"y":0,"w":28,"h":44},"rotated":false,"trimmed":false},"birds_r18_puffin_birds_r18_puffin_64_c_0_0.png":{"frame":{"x":92,"y":127,"w":30,"h":40},"sourceSize":{"w":30,"h":40},"spriteSourceSize":{"x":0,"y":0,"w":30,"h":40},"rotated":false,"trimmed":false},"birds_r18_puffin_birds_r18_puffin_64_c_0_6.png":{"frame":{"x":62,"y":169,"w":28,"h":44},"sourceSize":{"w":28,"h":44},"spriteSourceSize":{"x":0,"y":0,"w":28,"h":44},"rotated":false,"trimmed":false},"birds_r18_puffin_birds_r18_puffin_64_c_0_16.png":{"frame":{"x":124,"y":134,"w":31,"h":37},"sourceSize":{"w":31,"h":37},"spriteSourceSize":{"x":0,"y":0,"w":31,"h":37},"rotated":false,"trimmed":false},"birds_r18_puffin_birds_r18_puffin_64_d_0_1.png":{"frame":{"x":32,"y":33,"w":28,"h":42},"sourceSize":{"w":28,"h":42},"spriteSourceSize":{"x":0,"y":0,"w":28,"h":42},"rotated":false,"trimmed":false},"birds_r18_puffin_birds_r18_puffin_64_b_0_0.png":{"frame":{"x":2,"y":216,"w":42,"h":38},"sourceSize":{"w":42,"h":38},"spriteSourceSize":{"x":0,"y":0,"w":42,"h":38},"rotated":false,"trimmed":false},"birds_r18_puffin_birds_r18_puffin_64_d_0_13.png":{"frame":{"x":62,"y":2,"w":32,"h":35},"sourceSize":{"w":32,"h":35},"spriteSourceSize":{"x":0,"y":0,"w":32,"h":35},"rotated":false,"trimmed":false},"birds_r18_puffin_birds_r18_puffin_64_c_0_2.png":{"frame":{"x":2,"y":124,"w":28,"h":44},"sourceSize":{"w":28,"h":44},"spriteSourceSize":{"x":0,"y":0,"w":28,"h":44},"rotated":false,"trimmed":false},"birds_r18_puffin_birds_r18_puffin_64_a_0_0.png":{"frame":{"x":2,"y":8,"w":42,"h":22},"sourceSize":{"w":42,"h":22},"spriteSourceSize":{"x":0,"y":0,"w":42,"h":22},"rotated":false,"trimmed":false},"birds_r18_puffin_birds_r18_puffin_64_c_0_13.png":{"frame":{"x":157,"y":136,"w":32,"h":35},"sourceSize":{"w":32,"h":35},"spriteSourceSize":{"x":0,"y":0,"w":32,"h":35},"rotated":false,"trimmed":false},"birds_r18_puffin_birds_r18_puffin_64_d_0_6.png":{"frame":{"x":32,"y":77,"w":28,"h":44},"sourceSize":{"w":28,"h":44},"spriteSourceSize":{"x":0,"y":0,"w":28,"h":44},"rotated":false,"trimmed":false},"birds_r18_puffin_birds_r18_puffin_64_c_0_17.png":{"frame":{"x":178,"y":215,"w":31,"h":39},"sourceSize":{"w":31,"h":39},"spriteSourceSize":{"x":0,"y":0,"w":31,"h":39},"rotated":false,"trimmed":false},"birds_r18_puffin_birds_r18_puffin_64_d_0_10.png":{"frame":{"x":158,"y":65,"w":30,"h":31},"sourceSize":{"w":30,"h":31},"spriteSourceSize":{"x":0,"y":0,"w":30,"h":31},"rotated":false,"trimmed":false},"birds_r18_puffin_birds_r18_puffin_64_d_0_7.png":{"frame":{"x":62,"y":39,"w":30,"h":38},"sourceSize":{"w":30,"h":38},"spriteSourceSize":{"x":0,"y":0,"w":30,"h":38},"rotated":false,"trimmed":false},"birds_r18_puffin_birds_r18_puffin_64_d_0_2.png":{"frame":{"x":2,"y":170,"w":28,"h":44},"sourceSize":{"w":28,"h":44},"spriteSourceSize":{"x":0,"y":0,"w":28,"h":44},"rotated":false,"trimmed":false},"birds_r18_puffin_birds_r18_puffin_64_c_0_7.png":{"frame":{"x":92,"y":87,"w":30,"h":38},"sourceSize":{"w":30,"h":38},"spriteSourceSize":{"x":0,"y":0,"w":30,"h":38},"rotated":false,"trimmed":false},"birds_r18_puffin_birds_r18_puffin_64_d_0_14.png":{"frame":{"x":157,"y":98,"w":30,"h":36},"sourceSize":{"w":30,"h":36},"spriteSourceSize":{"x":0,"y":0,"w":30,"h":36},"rotated":false,"trimmed":false},"birds_r18_puffin_birds_r18_puffin_64_c_0_3.png":{"frame":{"x":62,"y":123,"w":28,"h":44},"sourceSize":{"w":28,"h":44},"spriteSourceSize":{"x":0,"y":0,"w":28,"h":44},"rotated":false,"trimmed":false},"birds_r18_puffin_birds_r18_puffin_64_c_0_14.png":{"frame":{"x":218,"y":177,"w":30,"h":36},"sourceSize":{"w":30,"h":36},"spriteSourceSize":{"x":0,"y":0,"w":30,"h":36},"rotated":false,"trimmed":false},"birds_r18_puffin_birds_r18_puffin_64_d_0_8.png":{"frame":{"x":222,"y":142,"w":29,"h":33},"sourceSize":{"w":29,"h":33},"spriteSourceSize":{"x":0,"y":0,"w":29,"h":33},"rotated":false,"trimmed":false},"birds_r18_puffin_birds_r18_puffin_64_d_0_3.png":{"frame":{"x":92,"y":169,"w":28,"h":44},"sourceSize":{"w":28,"h":44},"spriteSourceSize":{"x":0,"y":0,"w":28,"h":44},"rotated":false,"trimmed":false},"birds_r18_puffin_birds_r18_puffin_64_d_0_15.png":{"frame":{"x":46,"y":215,"w":31,"h":39},"sourceSize":{"w":31,"h":39},"spriteSourceSize":{"x":0,"y":0,"w":31,"h":39},"rotated":false,"trimmed":false},"birds_r18_puffin_birds_r18_puffin_icon_a.png":{"frame":{"x":189,"y":104,"w":23,"h":30},"sourceSize":{"w":23,"h":30},"spriteSourceSize":{"x":0,"y":0,"w":23,"h":30},"rotated":false,"trimmed":false},"birds_r18_puffin_birds_r18_puffin_64_d_0_11.png":{"frame":{"x":128,"y":28,"w":30,"h":31},"sourceSize":{"w":30,"h":31},"spriteSourceSize":{"x":0,"y":0,"w":30,"h":31},"rotated":false,"trimmed":false},"birds_r18_puffin_birds_r18_puffin_64_c_0_18.png":{"frame":{"x":122,"y":173,"w":30,"h":40},"sourceSize":{"w":30,"h":40},"spriteSourceSize":{"x":0,"y":0,"w":30,"h":40},"rotated":false,"trimmed":false},"birds_r18_puffin_birds_r18_puffin_64_c_0_8.png":{"frame":{"x":191,"y":138,"w":29,"h":33},"sourceSize":{"w":29,"h":33},"spriteSourceSize":{"x":0,"y":0,"w":29,"h":33},"rotated":false,"trimmed":false},"birds_r18_puffin_birds_r18_puffin_64_d_0_4.png":{"frame":{"x":32,"y":123,"w":28,"h":44},"sourceSize":{"w":28,"h":44},"spriteSourceSize":{"x":0,"y":0,"w":28,"h":44},"rotated":false,"trimmed":false},"birds_r18_puffin_birds_r18_puffin_64_c_0_15.png":{"frame":{"x":79,"y":215,"w":31,"h":39},"sourceSize":{"w":31,"h":39},"spriteSourceSize":{"x":0,"y":0,"w":31,"h":39},"rotated":false,"trimmed":false},"birds_r18_puffin_birds_r18_puffin_64_d_0_17.png":{"frame":{"x":211,"y":215,"w":31,"h":39},"sourceSize":{"w":31,"h":39},"spriteSourceSize":{"x":0,"y":0,"w":31,"h":39},"rotated":false,"trimmed":false},"birds_r18_puffin_birds_r18_puffin_64_c_0_4.png":{"frame":{"x":32,"y":169,"w":28,"h":44},"sourceSize":{"w":28,"h":44},"spriteSourceSize":{"x":0,"y":0,"w":28,"h":44},"rotated":false,"trimmed":false},"birds_r18_puffin_birds_r18_puffin_64_d_0_9.png":{"frame":{"x":126,"y":61,"w":30,"h":32},"sourceSize":{"w":30,"h":32},"spriteSourceSize":{"x":0,"y":0,"w":30,"h":32},"rotated":false,"trimmed":false},"birds_r18_puffin_birds_r18_puffin_64_c_0_10.png":{"frame":{"x":96,"y":20,"w":30,"h":31},"sourceSize":{"w":30,"h":31},"spriteSourceSize":{"x":0,"y":0,"w":30,"h":31},"rotated":false,"trimmed":false},"birds_r18_puffin_birds_r18_puffin_64_c_0_5.png":{"frame":{"x":2,"y":78,"w":28,"h":44},"sourceSize":{"w":28,"h":44},"spriteSourceSize":{"x":0,"y":0,"w":28,"h":44},"rotated":false,"trimmed":false},"birds_r18_puffin_birds_r18_puffin_64_d_0_16.png":{"frame":{"x":124,"y":95,"w":31,"h":37},"sourceSize":{"w":31,"h":37},"spriteSourceSize":{"x":0,"y":0,"w":31,"h":37},"rotated":false,"trimmed":false},"birds_r18_puffin_birds_r18_puffin_64_d_0_0.png":{"frame":{"x":186,"y":173,"w":30,"h":40},"sourceSize":{"w":30,"h":40},"spriteSourceSize":{"x":0,"y":0,"w":30,"h":40},"rotated":false,"trimmed":false},"birds_r18_puffin_birds_r18_puffin_64_c_0_9.png":{"frame":{"x":94,"y":53,"w":30,"h":32},"sourceSize":{"w":30,"h":32},"spriteSourceSize":{"x":0,"y":0,"w":30,"h":32},"rotated":false,"trimmed":false},"birds_r18_puffin_birds_r18_puffin_64_d_0_12.png":{"frame":{"x":112,"y":215,"w":31,"h":39},"sourceSize":{"w":31,"h":39},"spriteSourceSize":{"x":0,"y":0,"w":31,"h":39},"rotated":false,"trimmed":false}}}