{"type":"furniture","name":"hween13_gutsfloor","visualizationType":"furniture_animated","logicType":"furniture_multistate","spritesheet":{"meta":{"app":"FFConverter ~ Joopie","format":"RGBA8888","image":"hween13_gutsfloor.png","scale":"1.0","size":{"w":1024,"h":32},"version":"1.0"},"frames":{"hween13_gutsfloor_hween13_gutsfloor_64_a_0_2.png":{"frame":{"x":2,"y":2,"w":62,"h":27},"sourceSize":{"w":62,"h":27},"spriteSourceSize":{"x":0,"y":0,"w":62,"h":27},"rotated":false,"trimmed":false},"hween13_gutsfloor_hween13_gutsfloor_64_b_0_3.png":{"frame":{"x":496,"y":11,"w":51,"h":18},"sourceSize":{"w":51,"h":18},"spriteSourceSize":{"x":0,"y":0,"w":51,"h":18},"rotated":false,"trimmed":false},"hween13_gutsfloor_hween13_gutsfloor_64_b_0_2.png":{"frame":{"x":379,"y":2,"w":57,"h":27},"sourceSize":{"w":57,"h":27},"spriteSourceSize":{"x":0,"y":0,"w":57,"h":27},"rotated":false,"trimmed":false},"hween13_gutsfloor_hween13_gutsfloor_64_a_0_0.png":{"frame":{"x":194,"y":10,"w":62,"h":19},"sourceSize":{"w":62,"h":19},"spriteSourceSize":{"x":0,"y":0,"w":62,"h":19},"rotated":false,"trimmed":false},"hween13_gutsfloor_hween13_gutsfloor_64_a_0_3.png":{"frame":{"x":66,"y":6,"w":62,"h":23},"sourceSize":{"w":62,"h":23},"spriteSourceSize":{"x":0,"y":0,"w":62,"h":23},"rotated":false,"trimmed":false},"hween13_gutsfloor_hween13_gutsfloor_64_a_0_1.png":{"frame":{"x":130,"y":9,"w":62,"h":20},"sourceSize":{"w":62,"h":20},"spriteSourceSize":{"x":0,"y":0,"w":62,"h":20},"rotated":false,"trimmed":false},"hween13_gutsfloor_hween13_gutsfloor_64_sd_0_0.png":{"frame":{"x":258,"y":9,"w":60,"h":20},"sourceSize":{"w":60,"h":20},"spriteSourceSize":{"x":0,"y":0,"w":60,"h":20},"rotated":false,"trimmed":false},"hween13_gutsfloor_hween13_gutsfloor_64_b_0_0.png":{"frame":{"x":438,"y":7,"w":56,"h":22},"sourceSize":{"w":56,"h":22},"spriteSourceSize":{"x":0,"y":0,"w":56,"h":22},"rotated":false,"trimmed":false},"hween13_gutsfloor_hween13_gutsfloor_64_b_0_1.png":{"frame":{"x":320,"y":4,"w":57,"h":25},"sourceSize":{"w":57,"h":25},"spriteSourceSize":{"x":0,"y":0,"w":57,"h":25},"rotated":false,"trimmed":false},"hween13_gutsfloor_hween13_gutsfloor_icon_a.png":{"frame":{"x":549,"y":12,"w":29,"h":17},"sourceSize":{"w":29,"h":17},"spriteSourceSize":{"x":0,"y":0,"w":29,"h":17},"rotated":false,"trimmed":false}}},"dimensions":{"x":1.0,"y":1.0,"z":0.1},"directions":[0,180],"assets":{"hween13_gutsfloor_64_sd_4_0":{"source":"hween13_gutsfloor_64_sd_0_0","x":29,"y":2,"flipH":true},"hween13_gutsfloor_icon_a":{"x":14,"y":8},"hween13_gutsfloor_64_sd_0_0":{"x":29,"y":2},"hween13_gutsfloor_64_a_0_0":{"x":31,"y":15},"hween13_gutsfloor_64_a_0_1":{"x":31,"y":17},"hween13_gutsfloor_64_a_0_2":{"x":31,"y":24},"hween13_gutsfloor_64_a_0_3":{"x":31,"y":15},"hween13_gutsfloor_64_a_4_0":{"source":"hween13_gutsfloor_64_a_0_0","x":31,"y":15,"flipH":true},"hween13_gutsfloor_64_a_4_1":{"source":"hween13_gutsfloor_64_a_0_1","x":31,"y":17,"flipH":true},"hween13_gutsfloor_64_a_4_2":{"source":"hween13_gutsfloor_64_a_0_2","x":31,"y":24,"flipH":true},"hween13_gutsfloor_64_b_4_3":{"source":"hween13_gutsfloor_64_b_0_3","x":23,"y":1,"flipH":true},"hween13_gutsfloor_64_a_4_3":{"source":"hween13_gutsfloor_64_a_0_3","x":31,"y":15,"flipH":true},"hween13_gutsfloor_64_b_4_1":{"source":"hween13_gutsfloor_64_b_0_1","x":29,"y":8,"flipH":true},"hween13_gutsfloor_64_b_4_2":{"source":"hween13_gutsfloor_64_b_0_2","x":29,"y":10,"flipH":true},"hween13_gutsfloor_64_b_0_3":{"x":23,"y":1},"hween13_gutsfloor_64_b_4_0":{"source":"hween13_gutsfloor_64_b_0_0","x":28,"y":5,"flipH":true},"hween13_gutsfloor_64_b_0_1":{"x":29,"y":8},"hween13_gutsfloor_64_b_0_2":{"x":29,"y":10},"hween13_gutsfloor_64_b_0_0":{"x":28,"y":5}},"visualizations":[{"layerCount":1,"angle":360,"size":1},{"layerCount":2,"angle":45,"size":64,"layers":{"0":{},"1":{"z":500.0}},"directions":{"0":{},"4":{}},"animations":{"0":{"layers":{"0":{"loopCount":0,"frameRepeat":2,"frameSequences":{"0":{"frames":{"0":{"id":0},"1":{"id":1},"2":{"id":2},"3":{"id":1},"4":{"id":0},"5":{"id":3},"6":{"id":0},"7":{"id":1},"8":{"id":2},"9":{"id":1},"10":{"id":0},"11":{"id":3},"12":{"id":0},"13":{"id":0},"14":{"id":0},"15":{"id":0},"16":{"id":0},"17":{"id":0},"18":{"id":0},"19":{"id":0},"20":{"id":0},"21":{"id":0},"22":{"id":0},"23":{"id":0},"24":{"id":0},"25":{"id":0},"26":{"id":0},"27":{"id":0},"28":{"id":0},"29":{"id":0},"30":{"id":0},"31":{"id":0},"32":{"id":0},"33":{"id":0},"34":{"id":0},"35":{"id":0},"36":{"id":0},"37":{"id":0},"38":{"id":0},"39":{"id":0},"40":{"id":0},"41":{"id":0},"42":{"id":0}}}}},"1":{"loopCount":0,"frameRepeat":2,"frameSequences":{"0":{"frames":{"0":{"id":0},"1":{"id":1},"2":{"id":2},"3":{"id":1},"4":{"id":0},"5":{"id":3},"6":{"id":0},"7":{"id":1},"8":{"id":2},"9":{"id":1},"10":{"id":0},"11":{"id":3},"12":{"id":0},"13":{"id":0},"14":{"id":0},"15":{"id":0},"16":{"id":0},"17":{"id":0},"18":{"id":0},"19":{"id":0},"20":{"id":0},"21":{"id":0},"22":{"id":0},"23":{"id":0},"24":{"id":0},"25":{"id":0},"26":{"id":0},"27":{"id":0},"28":{"id":0},"29":{"id":0},"30":{"id":0},"31":{"id":0},"32":{"id":0},"33":{"id":0},"34":{"id":0},"35":{"id":0},"36":{"id":0},"37":{"id":0},"38":{"id":0},"39":{"id":0},"40":{"id":0},"41":{"id":0},"42":{"id":0}}}}}}}}}]}