{"meta":{"app":"Holo5-Excavator ~ Holo5 (github:Pi-Bouf)","format":"RGBA8888","image":"jacket_M_sport5.png","scale":"1.0","size":{"w":253,"h":233},"version":"1.0"},"frames":{"jacket_M_sport5_h_lay_cc_8956_2_0":{"frame":{"x":0,"y":0,"w":36,"h":29},"sourceSize":{"w":36,"h":29},"spriteSourceSize":{"x":-4,"y":-27,"w":36,"h":29},"rotated":false,"trimmed":true},"jacket_M_sport5_h_std_cc_8956_2_0":{"frame":{"x":0,"y":29,"w":28,"h":35},"sourceSize":{"w":28,"h":35},"spriteSourceSize":{"x":20,"y":-51,"w":28,"h":35},"rotated":false,"trimmed":true},"jacket_M_sport5_h_std_cc_8956_0_0":{"frame":{"x":36,"y":0,"w":26,"h":33},"sourceSize":{"w":26,"h":33},"spriteSourceSize":{"x":18,"y":-49,"w":26,"h":33},"rotated":false,"trimmed":true},"jacket_M_sport5_h_std_cc_8956_3_0":{"frame":{"x":36,"y":33,"w":25,"h":31},"sourceSize":{"w":25,"h":31},"spriteSourceSize":{"x":21,"y":-50,"w":25,"h":31},"rotated":false,"trimmed":true},"jacket_M_sport5_h_std_cc_8956_7_0":{"frame":{"x":62,"y":0,"w":25,"h":31},"sourceSize":{"w":25,"h":31},"spriteSourceSize":{"x":21,"y":-48,"w":25,"h":31},"rotated":false,"trimmed":true},"jacket_M_sport5_h_std_cc_8956_1_0":{"frame":{"x":62,"y":31,"w":22,"h":32},"sourceSize":{"w":22,"h":32},"spriteSourceSize":{"x":22,"y":-49,"w":22,"h":32},"rotated":false,"trimmed":true},"jacket_M_sport5_h_lay_cc_8958_2_0":{"frame":{"x":87,"y":0,"w":28,"h":24},"sourceSize":{"w":28,"h":24},"spriteSourceSize":{"x":-2,"y":-26,"w":28,"h":24},"rotated":false,"trimmed":true},"jacket_M_sport5_h_std_cc_8958_2_0":{"frame":{"x":87,"y":24,"w":24,"h":26},"sourceSize":{"w":24,"h":26},"spriteSourceSize":{"x":21,"y":-50,"w":24,"h":26},"rotated":false,"trimmed":true},"jacket_M_sport5_h_std_cc_8958_0_0":{"frame":{"x":0,"y":64,"w":24,"h":24},"sourceSize":{"w":24,"h":24},"spriteSourceSize":{"x":19,"y":-48,"w":24,"h":24},"rotated":false,"trimmed":true},"jacket_M_sport5_h_std_cc_8958_7_0":{"frame":{"x":24,"y":64,"w":23,"h":24},"sourceSize":{"w":23,"h":24},"spriteSourceSize":{"x":22,"y":-47,"w":23,"h":24},"rotated":false,"trimmed":true},"jacket_M_sport5_h_std_cc_8958_3_0":{"frame":{"x":47,"y":64,"w":23,"h":22},"sourceSize":{"w":23,"h":22},"spriteSourceSize":{"x":22,"y":-47,"w":23,"h":22},"rotated":false,"trimmed":true},"jacket_M_sport5_h_std_cc_8957_2_0":{"frame":{"x":70,"y":64,"w":24,"h":21},"sourceSize":{"w":24,"h":21},"spriteSourceSize":{"x":21,"y":-48,"w":24,"h":21},"rotated":false,"trimmed":true},"jacket_M_sport5_h_wav_lc_8956_3_1":{"frame":{"x":115,"y":0,"w":18,"h":28},"sourceSize":{"w":18,"h":28},"spriteSourceSize":{"x":43,"y":-64,"w":18,"h":28},"rotated":false,"trimmed":true},"jacket_M_sport5_h_wav_lc_8956_6_1":{"frame":{"x":0,"y":88,"w":21,"h":24},"sourceSize":{"w":21,"h":24},"spriteSourceSize":{"x":8,"y":-58,"w":21,"h":24},"rotated":false,"trimmed":true},"jacket_M_sport5_h_wav_lc_8956_7_1":{"frame":{"x":115,"y":28,"w":18,"h":28},"sourceSize":{"w":18,"h":28},"spriteSourceSize":{"x":7,"y":-63,"w":18,"h":28},"rotated":false,"trimmed":true},"jacket_M_sport5_h_wav_lc_8956_4_0":{"frame":{"x":133,"y":0,"w":19,"h":26},"sourceSize":{"w":19,"h":26},"spriteSourceSize":{"x":40,"y":-60,"w":19,"h":26},"rotated":false,"trimmed":true},"jacket_M_sport5_h_std_cc_8957_0_0":{"frame":{"x":21,"y":88,"w":24,"h":20},"sourceSize":{"w":24,"h":20},"spriteSourceSize":{"x":19,"y":-47,"w":24,"h":20},"rotated":false,"trimmed":true},"jacket_M_sport5_h_wav_lc_8956_6_0":{"frame":{"x":133,"y":26,"w":19,"h":25},"sourceSize":{"w":19,"h":25},"spriteSourceSize":{"x":10,"y":-59,"w":19,"h":25},"rotated":false,"trimmed":true},"jacket_M_sport5_h_std_cc_8957_7_0":{"frame":{"x":45,"y":88,"w":23,"h":20},"sourceSize":{"w":23,"h":20},"spriteSourceSize":{"x":22,"y":-45,"w":23,"h":20},"rotated":false,"trimmed":true},"jacket_M_sport5_h_wav_lc_8956_5_0":{"frame":{"x":133,"y":51,"w":17,"h":27},"sourceSize":{"w":17,"h":27},"spriteSourceSize":{"x":21,"y":-63,"w":17,"h":27},"rotated":false,"trimmed":true},"jacket_M_sport5_h_crr_lc_8956_4_0":{"frame":{"x":133,"y":78,"w":18,"h":25},"sourceSize":{"w":18,"h":25},"spriteSourceSize":{"x":31,"y":-46,"w":18,"h":25},"rotated":false,"trimmed":true},"jacket_M_sport5_h_crr_rc_8956_2_0":{"frame":{"x":115,"y":56,"w":18,"h":25},"sourceSize":{"w":18,"h":25},"spriteSourceSize":{"x":17,"y":-46,"w":18,"h":25},"rotated":false,"trimmed":true},"jacket_M_sport5_h_wlk_rc_8956_2_3":{"frame":{"x":0,"y":112,"w":15,"h":30},"sourceSize":{"w":15,"h":30},"spriteSourceSize":{"x":17,"y":-47,"w":15,"h":30},"rotated":false,"trimmed":true},"jacket_M_sport5_h_lay_cc_8957_2_0":{"frame":{"x":68,"y":88,"w":26,"h":17},"sourceSize":{"w":26,"h":17},"spriteSourceSize":{"x":-2,"y":-20,"w":26,"h":17},"rotated":false,"trimmed":true},"jacket_M_sport5_h_wav_lc_8956_4_1":{"frame":{"x":15,"y":112,"w":17,"h":26},"sourceSize":{"w":17,"h":26},"spriteSourceSize":{"x":40,"y":-60,"w":17,"h":26},"rotated":false,"trimmed":true},"jacket_M_sport5_h_crr_rc_8956_4_0":{"frame":{"x":32,"y":112,"w":18,"h":24},"sourceSize":{"w":18,"h":24},"spriteSourceSize":{"x":12,"y":-51,"w":18,"h":24},"rotated":false,"trimmed":true},"jacket_M_sport5_h_wav_lc_8956_2_1":{"frame":{"x":50,"y":112,"w":18,"h":24},"sourceSize":{"w":18,"h":24},"spriteSourceSize":{"x":39,"y":-64,"w":18,"h":24},"rotated":false,"trimmed":true},"jacket_M_sport5_h_wav_lc_8956_5_1":{"frame":{"x":152,"y":0,"w":16,"h":27},"sourceSize":{"w":16,"h":27},"spriteSourceSize":{"x":22,"y":-63,"w":16,"h":27},"rotated":false,"trimmed":true},"jacket_M_sport5_h_wav_lc_8956_3_0":{"frame":{"x":152,"y":27,"w":15,"h":28},"sourceSize":{"w":15,"h":28},"spriteSourceSize":{"x":43,"y":-64,"w":15,"h":28},"rotated":false,"trimmed":true},"jacket_M_sport5_h_wav_lc_8956_7_0":{"frame":{"x":152,"y":55,"w":15,"h":28},"sourceSize":{"w":15,"h":28},"spriteSourceSize":{"x":10,"y":-63,"w":15,"h":28},"rotated":false,"trimmed":true},"jacket_M_sport5_h_drk_rc_8956_3_0":{"frame":{"x":68,"y":112,"w":19,"h":22},"sourceSize":{"w":19,"h":22},"spriteSourceSize":{"x":15,"y":-49,"w":19,"h":22},"rotated":false,"trimmed":true},"jacket_M_sport5_h_std_cc_8957_3_0":{"frame":{"x":87,"y":112,"w":23,"h":18},"sourceSize":{"w":23,"h":18},"spriteSourceSize":{"x":22,"y":-46,"w":23,"h":18},"rotated":false,"trimmed":true},"jacket_M_sport5_h_std_cc_8958_1_0":{"frame":{"x":0,"y":142,"w":17,"h":24},"sourceSize":{"w":17,"h":24},"spriteSourceSize":{"x":23,"y":-48,"w":17,"h":24},"rotated":false,"trimmed":true},"jacket_M_sport5_h_drk_rc_8956_6_0":{"frame":{"x":94,"y":88,"w":27,"h":15},"sourceSize":{"w":27,"h":15},"spriteSourceSize":{"x":19,"y":-51,"w":27,"h":15},"rotated":false,"trimmed":true},"jacket_M_sport5_h_drk_rc_8956_4_0":{"frame":{"x":94,"y":64,"w":20,"h":20},"sourceSize":{"w":20,"h":20},"spriteSourceSize":{"x":10,"y":-51,"w":20,"h":20},"rotated":false,"trimmed":true},"jacket_M_sport5_h_wav_lc_8956_2_0":{"frame":{"x":152,"y":83,"w":16,"h":25},"sourceSize":{"w":16,"h":25},"spriteSourceSize":{"x":39,"y":-65,"w":16,"h":25},"rotated":false,"trimmed":true},"jacket_M_sport5_h_drk_rc_8956_0_0":{"frame":{"x":17,"y":142,"w":21,"h":19},"sourceSize":{"w":21,"h":19},"spriteSourceSize":{"x":35,"y":-52,"w":21,"h":19},"rotated":false,"trimmed":true},"jacket_M_sport5_h_lay_rc_8956_2_0":{"frame":{"x":110,"y":112,"w":22,"h":18},"sourceSize":{"w":22,"h":18},"spriteSourceSize":{"x":-6,"y":-16,"w":22,"h":18},"rotated":false,"trimmed":true},"jacket_M_sport5_h_crr_lc_8956_0_0":{"frame":{"x":168,"y":0,"w":17,"h":23},"sourceSize":{"w":17,"h":23},"spriteSourceSize":{"x":16,"y":-48,"w":17,"h":23},"rotated":false,"trimmed":true},"jacket_M_sport5_h_crr_lc_8956_6_0":{"frame":{"x":168,"y":23,"w":17,"h":23},"sourceSize":{"w":17,"h":23},"spriteSourceSize":{"x":14,"y":-44,"w":17,"h":23},"rotated":false,"trimmed":true},"jacket_M_sport5_h_crr_rc_8956_6_0":{"frame":{"x":168,"y":46,"w":17,"h":23},"sourceSize":{"w":17,"h":23},"spriteSourceSize":{"x":31,"y":-48,"w":17,"h":23},"rotated":false,"trimmed":true},"jacket_M_sport5_h_wlk_rc_8956_1_3":{"frame":{"x":168,"y":69,"w":17,"h":23},"sourceSize":{"w":17,"h":23},"spriteSourceSize":{"x":26,"y":-42,"w":17,"h":23},"rotated":false,"trimmed":true},"jacket_M_sport5_h_drk_rc_8956_2_0":{"frame":{"x":38,"y":142,"w":24,"h":16},"sourceSize":{"w":24,"h":16},"spriteSourceSize":{"x":22,"y":-44,"w":24,"h":16},"rotated":false,"trimmed":true},"jacket_M_sport5_h_crr_rc_8956_0_0":{"frame":{"x":168,"y":92,"w":17,"h":22},"sourceSize":{"w":17,"h":22},"spriteSourceSize":{"x":36,"y":-43,"w":17,"h":22},"rotated":false,"trimmed":true},"jacket_M_sport5_h_wav_lc_8956_0_1":{"frame":{"x":168,"y":114,"w":16,"h":23},"sourceSize":{"w":16,"h":23},"spriteSourceSize":{"x":8,"y":-62,"w":16,"h":23},"rotated":false,"trimmed":true},"jacket_M_sport5_h_wlk_rc_8956_2_1":{"frame":{"x":168,"y":137,"w":13,"h":27},"sourceSize":{"w":13,"h":27},"spriteSourceSize":{"x":15,"y":-45,"w":13,"h":27},"rotated":false,"trimmed":true},"jacket_M_sport5_h_wav_lc_8956_0_0":{"frame":{"x":152,"y":108,"w":14,"h":25},"sourceSize":{"w":14,"h":25},"spriteSourceSize":{"x":10,"y":-64,"w":14,"h":25},"rotated":false,"trimmed":true},"jacket_M_sport5_h_wlk_rc_8956_2_2":{"frame":{"x":185,"y":0,"w":12,"h":29},"sourceSize":{"w":12,"h":29},"spriteSourceSize":{"x":16,"y":-47,"w":12,"h":29},"rotated":false,"trimmed":true},"jacket_M_sport5_h_std_cc_8957_1_0":{"frame":{"x":0,"y":166,"w":17,"h":20},"sourceSize":{"w":17,"h":20},"spriteSourceSize":{"x":23,"y":-47,"w":17,"h":20},"rotated":false,"trimmed":true},"jacket_M_sport5_h_crr_lc_8956_1_0":{"frame":{"x":197,"y":0,"w":16,"h":21},"sourceSize":{"w":16,"h":21},"spriteSourceSize":{"x":26,"y":-44,"w":16,"h":21},"rotated":false,"trimmed":true},"jacket_M_sport5_h_crr_lc_8956_5_0":{"frame":{"x":197,"y":21,"w":16,"h":21},"sourceSize":{"w":16,"h":21},"spriteSourceSize":{"x":24,"y":-42,"w":16,"h":21},"rotated":false,"trimmed":true},"jacket_M_sport5_h_crr_rc_8956_1_0":{"frame":{"x":197,"y":42,"w":16,"h":21},"sourceSize":{"w":16,"h":21},"spriteSourceSize":{"x":26,"y":-42,"w":16,"h":21},"rotated":false,"trimmed":true},"jacket_M_sport5_h_crr_rc_8956_5_0":{"frame":{"x":197,"y":63,"w":16,"h":21},"sourceSize":{"w":16,"h":21},"spriteSourceSize":{"x":24,"y":-44,"w":16,"h":21},"rotated":false,"trimmed":true},"jacket_M_sport5_h_drk_rc_8956_1_0":{"frame":{"x":87,"y":50,"w":24,"h":14},"sourceSize":{"w":24,"h":14},"spriteSourceSize":{"x":28,"y":-46,"w":24,"h":14},"rotated":false,"trimmed":true},"jacket_M_sport5_h_drk_rc_8956_5_0":{"frame":{"x":62,"y":142,"w":24,"h":14},"sourceSize":{"w":24,"h":14},"spriteSourceSize":{"x":10,"y":-46,"w":24,"h":14},"rotated":false,"trimmed":true},"jacket_M_sport5_h_wlk_rc_8956_2_0":{"frame":{"x":197,"y":84,"w":12,"h":28},"sourceSize":{"w":12,"h":28},"spriteSourceSize":{"x":16,"y":-46,"w":12,"h":28},"rotated":false,"trimmed":true},"jacket_M_sport5_h_crr_lc_8956_2_0":{"frame":{"x":197,"y":112,"w":15,"h":22},"sourceSize":{"w":15,"h":22},"spriteSourceSize":{"x":39,"y":-48,"w":15,"h":22},"rotated":false,"trimmed":true},"jacket_M_sport5_h_wlk_rc_8956_0_1":{"frame":{"x":197,"y":134,"w":13,"h":25},"sourceSize":{"w":13,"h":25},"spriteSourceSize":{"x":34,"y":-43,"w":13,"h":25},"rotated":false,"trimmed":true},"jacket_M_sport5_h_wlk_rc_8956_0_3":{"frame":{"x":197,"y":159,"w":13,"h":25},"sourceSize":{"w":13,"h":25},"spriteSourceSize":{"x":37,"y":-43,"w":13,"h":25},"rotated":false,"trimmed":true},"jacket_M_sport5_h_drk_rc_8956_7_0":{"frame":{"x":0,"y":186,"w":13,"h":24},"sourceSize":{"w":13,"h":24},"spriteSourceSize":{"x":39,"y":-48,"w":13,"h":24},"rotated":false,"trimmed":true},"jacket_M_sport5_h_wlk_rc_8956_0_0":{"frame":{"x":185,"y":29,"w":12,"h":25},"sourceSize":{"w":12,"h":25},"spriteSourceSize":{"x":36,"y":-43,"w":12,"h":25},"rotated":false,"trimmed":true},"jacket_M_sport5_h_wlk_rc_8956_0_2":{"frame":{"x":185,"y":54,"w":12,"h":25},"sourceSize":{"w":12,"h":25},"spriteSourceSize":{"x":36,"y":-43,"w":12,"h":25},"rotated":false,"trimmed":true},"jacket_M_sport5_h_std_rc_8956_0_0":{"frame":{"x":185,"y":79,"w":11,"h":27},"sourceSize":{"w":11,"h":27},"spriteSourceSize":{"x":37,"y":-43,"w":11,"h":27},"rotated":false,"trimmed":true},"jacket_M_sport5_h_wlk_lc_8956_3_1":{"frame":{"x":185,"y":106,"w":10,"h":29},"sourceSize":{"w":10,"h":29},"spriteSourceSize":{"x":42,"y":-49,"w":10,"h":29},"rotated":false,"trimmed":true},"jacket_M_sport5_h_wlk_rc_8956_3_3":{"frame":{"x":185,"y":135,"w":10,"h":29},"sourceSize":{"w":10,"h":29},"spriteSourceSize":{"x":15,"y":-49,"w":10,"h":29},"rotated":false,"trimmed":true},"jacket_M_sport5_h_wlk_lc_8956_1_0":{"frame":{"x":13,"y":186,"w":12,"h":24},"sourceSize":{"w":12,"h":24},"spriteSourceSize":{"x":25,"y":-45,"w":12,"h":24},"rotated":false,"trimmed":true},"jacket_M_sport5_h_wlk_lc_8956_1_2":{"frame":{"x":25,"y":186,"w":12,"h":24},"sourceSize":{"w":12,"h":24},"spriteSourceSize":{"x":25,"y":-45,"w":12,"h":24},"rotated":false,"trimmed":true},"jacket_M_sport5_h_std_rc_8956_2_0":{"frame":{"x":213,"y":0,"w":11,"h":26},"sourceSize":{"w":11,"h":26},"spriteSourceSize":{"x":17,"y":-44,"w":11,"h":26},"rotated":false,"trimmed":true},"jacket_M_sport5_h_std_lc_8956_3_0":{"frame":{"x":213,"y":26,"w":10,"h":28},"sourceSize":{"w":10,"h":28},"spriteSourceSize":{"x":42,"y":-49,"w":10,"h":28},"rotated":false,"trimmed":true},"jacket_M_sport5_h_std_rc_8956_3_0":{"frame":{"x":213,"y":54,"w":10,"h":28},"sourceSize":{"w":10,"h":28},"spriteSourceSize":{"x":15,"y":-49,"w":10,"h":28},"rotated":false,"trimmed":true},"jacket_M_sport5_h_wlk_lc_8956_3_0":{"frame":{"x":213,"y":82,"w":10,"h":28},"sourceSize":{"w":10,"h":28},"spriteSourceSize":{"x":42,"y":-49,"w":10,"h":28},"rotated":false,"trimmed":true},"jacket_M_sport5_h_wlk_lc_8956_3_2":{"frame":{"x":213,"y":110,"w":10,"h":28},"sourceSize":{"w":10,"h":28},"spriteSourceSize":{"x":42,"y":-49,"w":10,"h":28},"rotated":false,"trimmed":true},"jacket_M_sport5_h_wlk_rc_8956_3_0":{"frame":{"x":213,"y":138,"w":10,"h":28},"sourceSize":{"w":10,"h":28},"spriteSourceSize":{"x":15,"y":-49,"w":10,"h":28},"rotated":false,"trimmed":true},"jacket_M_sport5_h_wlk_rc_8956_3_2":{"frame":{"x":213,"y":166,"w":10,"h":28},"sourceSize":{"w":10,"h":28},"spriteSourceSize":{"x":15,"y":-49,"w":10,"h":28},"rotated":false,"trimmed":true},"jacket_M_sport5_h_wav_lc_8956_1_0":{"frame":{"x":37,"y":186,"w":12,"h":23},"sourceSize":{"w":12,"h":23},"spriteSourceSize":{"x":31,"y":-65,"w":12,"h":23},"rotated":false,"trimmed":true},"jacket_M_sport5_h_wav_lc_8956_1_1":{"frame":{"x":49,"y":186,"w":12,"h":23},"sourceSize":{"w":12,"h":23},"spriteSourceSize":{"x":32,"y":-65,"w":12,"h":23},"rotated":false,"trimmed":true},"jacket_M_sport5_h_wlk_rc_8956_1_0":{"frame":{"x":61,"y":186,"w":12,"h":23},"sourceSize":{"w":12,"h":23},"spriteSourceSize":{"x":25,"y":-42,"w":12,"h":23},"rotated":false,"trimmed":true},"jacket_M_sport5_h_wlk_rc_8956_1_2":{"frame":{"x":73,"y":186,"w":12,"h":23},"sourceSize":{"w":12,"h":23},"spriteSourceSize":{"x":25,"y":-42,"w":12,"h":23},"rotated":false,"trimmed":true},"jacket_M_sport5_h_wlk_rc_8956_1_1":{"frame":{"x":85,"y":186,"w":13,"h":21},"sourceSize":{"w":13,"h":21},"spriteSourceSize":{"x":21,"y":-42,"w":13,"h":21},"rotated":false,"trimmed":true},"jacket_M_sport5_h_wlk_lc_8956_7_3":{"frame":{"x":224,"y":0,"w":10,"h":27},"sourceSize":{"w":10,"h":27},"spriteSourceSize":{"x":15,"y":-45,"w":10,"h":27},"rotated":false,"trimmed":true},"jacket_M_sport5_h_wlk_rc_8956_7_1":{"frame":{"x":224,"y":27,"w":10,"h":27},"sourceSize":{"w":10,"h":27},"spriteSourceSize":{"x":42,"y":-45,"w":10,"h":27},"rotated":false,"trimmed":true},"jacket_M_sport5_h_wlk_rc_8956_7_2":{"frame":{"x":224,"y":54,"w":10,"h":27},"sourceSize":{"w":10,"h":27},"spriteSourceSize":{"x":42,"y":-46,"w":10,"h":27},"rotated":false,"trimmed":true},"jacket_M_sport5_h_std_lc_8956_7_0":{"frame":{"x":224,"y":81,"w":10,"h":26},"sourceSize":{"w":10,"h":26},"spriteSourceSize":{"x":15,"y":-45,"w":10,"h":26},"rotated":false,"trimmed":true},"jacket_M_sport5_h_std_rc_8956_7_0":{"frame":{"x":224,"y":107,"w":10,"h":26},"sourceSize":{"w":10,"h":26},"spriteSourceSize":{"x":42,"y":-45,"w":10,"h":26},"rotated":false,"trimmed":true},"jacket_M_sport5_h_wlk_lc_8956_7_0":{"frame":{"x":224,"y":133,"w":10,"h":26},"sourceSize":{"w":10,"h":26},"spriteSourceSize":{"x":15,"y":-45,"w":10,"h":26},"rotated":false,"trimmed":true},"jacket_M_sport5_h_wlk_lc_8956_7_2":{"frame":{"x":224,"y":159,"w":10,"h":26},"sourceSize":{"w":10,"h":26},"spriteSourceSize":{"x":15,"y":-45,"w":10,"h":26},"rotated":false,"trimmed":true},"jacket_M_sport5_h_wlk_rc_8956_7_0":{"frame":{"x":234,"y":0,"w":10,"h":26},"sourceSize":{"w":10,"h":26},"spriteSourceSize":{"x":42,"y":-45,"w":10,"h":26},"rotated":false,"trimmed":true},"jacket_M_sport5_h_wlk_rc_8956_7_3":{"frame":{"x":234,"y":26,"w":10,"h":26},"sourceSize":{"w":10,"h":26},"spriteSourceSize":{"x":42,"y":-46,"w":10,"h":26},"rotated":false,"trimmed":true},"jacket_M_sport5_h_std_lc_8956_1_0":{"frame":{"x":0,"y":210,"w":11,"h":23},"sourceSize":{"w":11,"h":23},"spriteSourceSize":{"x":26,"y":-44,"w":11,"h":23},"rotated":false,"trimmed":true},"jacket_M_sport5_h_std_rc_8956_1_0":{"frame":{"x":11,"y":210,"w":11,"h":23},"sourceSize":{"w":11,"h":23},"spriteSourceSize":{"x":26,"y":-42,"w":11,"h":23},"rotated":false,"trimmed":true},"jacket_M_sport5_h_crr_lc_8956_3_0":{"frame":{"x":234,"y":52,"w":10,"h":25},"sourceSize":{"w":10,"h":25},"spriteSourceSize":{"x":41,"y":-49,"w":10,"h":25},"rotated":false,"trimmed":true},"jacket_M_sport5_h_crr_rc_8956_3_0":{"frame":{"x":234,"y":77,"w":10,"h":25},"sourceSize":{"w":10,"h":25},"spriteSourceSize":{"x":15,"y":-49,"w":10,"h":25},"rotated":false,"trimmed":true},"jacket_M_sport5_h_wlk_lc_8956_2_1":{"frame":{"x":234,"y":102,"w":10,"h":25},"sourceSize":{"w":10,"h":25},"spriteSourceSize":{"x":42,"y":-48,"w":10,"h":25},"rotated":false,"trimmed":true},"jacket_M_sport5_h_wlk_lc_8956_3_3":{"frame":{"x":234,"y":127,"w":10,"h":25},"sourceSize":{"w":10,"h":25},"spriteSourceSize":{"x":42,"y":-49,"w":10,"h":25},"rotated":false,"trimmed":true},"jacket_M_sport5_h_wlk_lc_8956_7_1":{"frame":{"x":234,"y":152,"w":10,"h":25},"sourceSize":{"w":10,"h":25},"spriteSourceSize":{"x":15,"y":-45,"w":10,"h":25},"rotated":false,"trimmed":true},"jacket_M_sport5_h_wlk_rc_8956_3_1":{"frame":{"x":234,"y":177,"w":10,"h":25},"sourceSize":{"w":10,"h":25},"spriteSourceSize":{"x":15,"y":-49,"w":10,"h":25},"rotated":false,"trimmed":true},"jacket_M_sport5_h_wlk_lc_8956_0_3":{"frame":{"x":244,"y":0,"w":9,"h":26},"sourceSize":{"w":9,"h":26},"spriteSourceSize":{"x":13,"y":-48,"w":9,"h":26},"rotated":false,"trimmed":true},"jacket_M_sport5_h_lay_lc_8956_2_0":{"frame":{"x":86,"y":142,"w":23,"h":10},"sourceSize":{"w":23,"h":10},"spriteSourceSize":{"x":12,"y":-23,"w":23,"h":10},"rotated":false,"trimmed":true},"jacket_M_sport5_h_crr_lc_8956_7_0":{"frame":{"x":224,"y":185,"w":10,"h":21},"sourceSize":{"w":10,"h":21},"spriteSourceSize":{"x":15,"y":-45,"w":10,"h":21},"rotated":false,"trimmed":true},"jacket_M_sport5_h_crr_rc_8956_7_0":{"frame":{"x":98,"y":186,"w":10,"h":21},"sourceSize":{"w":10,"h":21},"spriteSourceSize":{"x":42,"y":-45,"w":10,"h":21},"rotated":false,"trimmed":true},"jacket_M_sport5_h_wlk_lc_8956_2_0":{"frame":{"x":244,"y":26,"w":8,"h":23},"sourceSize":{"w":8,"h":23},"spriteSourceSize":{"x":42,"y":-48,"w":8,"h":23},"rotated":false,"trimmed":true},"jacket_M_sport5_h_wlk_lc_8956_2_2":{"frame":{"x":244,"y":49,"w":8,"h":23},"sourceSize":{"w":8,"h":23},"spriteSourceSize":{"x":42,"y":-48,"w":8,"h":23},"rotated":false,"trimmed":true},"jacket_M_sport5_h_wlk_lc_8956_0_1":{"frame":{"x":244,"y":72,"w":8,"h":21},"sourceSize":{"w":8,"h":21},"spriteSourceSize":{"x":15,"y":-48,"w":8,"h":21},"rotated":false,"trimmed":true},"jacket_M_sport5_h_std_lc_8956_0_0":{"frame":{"x":244,"y":93,"w":7,"h":23},"sourceSize":{"w":7,"h":23},"spriteSourceSize":{"x":15,"y":-48,"w":7,"h":23},"rotated":false,"trimmed":true},"jacket_M_sport5_h_std_lc_8956_2_0":{"frame":{"x":244,"y":116,"w":7,"h":23},"sourceSize":{"w":7,"h":23},"spriteSourceSize":{"x":43,"y":-48,"w":7,"h":23},"rotated":false,"trimmed":true},"jacket_M_sport5_h_wlk_lc_8956_0_0":{"frame":{"x":244,"y":139,"w":7,"h":23},"sourceSize":{"w":7,"h":23},"spriteSourceSize":{"x":15,"y":-48,"w":7,"h":23},"rotated":false,"trimmed":true},"jacket_M_sport5_h_wlk_lc_8956_0_2":{"frame":{"x":244,"y":162,"w":7,"h":23},"sourceSize":{"w":7,"h":23},"spriteSourceSize":{"x":15,"y":-48,"w":7,"h":23},"rotated":false,"trimmed":true},"jacket_M_sport5_h_wlk_lc_8956_1_3":{"frame":{"x":244,"y":185,"w":7,"h":21},"sourceSize":{"w":7,"h":21},"spriteSourceSize":{"x":19,"y":-42,"w":7,"h":21},"rotated":false,"trimmed":true},"jacket_M_sport5_h_wlk_lc_8956_2_3":{"frame":{"x":244,"y":206,"w":7,"h":15},"sourceSize":{"w":7,"h":15},"spriteSourceSize":{"x":42,"y":-48,"w":7,"h":15},"rotated":false,"trimmed":true},"jacket_M_sport5_h_wlk_lc_8956_1_1":{"frame":{"x":244,"y":221,"w":7,"h":7},"sourceSize":{"w":7,"h":7},"spriteSourceSize":{"x":34,"y":-29,"w":7,"h":7},"rotated":false,"trimmed":true}},"animations":{"cc_8956_lay_2":["jacket_M_sport5_h_lay_cc_8956_2_0"],"cc_8956_lay_4":["jacket_M_sport5_h_lay_cc_8956_2_0"],"cc_8956_std_0":["jacket_M_sport5_h_std_cc_8956_0_0"],"cc_8956_std_1":["jacket_M_sport5_h_std_cc_8956_1_0"],"cc_8956_std_2":["jacket_M_sport5_h_std_cc_8956_2_0"],"cc_8956_std_3":["jacket_M_sport5_h_std_cc_8956_3_0"],"cc_8956_std_4":["jacket_M_sport5_h_std_cc_8956_2_0"],"cc_8956_std_5":["jacket_M_sport5_h_std_cc_8956_1_0"],"cc_8956_std_6":["jacket_M_sport5_h_std_cc_8956_0_0"],"cc_8956_std_7":["jacket_M_sport5_h_std_cc_8956_7_0"],"cc_8958_lay_2":["jacket_M_sport5_h_lay_cc_8958_2_0"],"cc_8958_lay_4":["jacket_M_sport5_h_lay_cc_8958_2_0"],"cc_8958_std_0":["jacket_M_sport5_h_std_cc_8958_0_0"],"cc_8958_std_1":["jacket_M_sport5_h_std_cc_8958_1_0"],"cc_8958_std_2":["jacket_M_sport5_h_std_cc_8958_2_0"],"cc_8958_std_3":["jacket_M_sport5_h_std_cc_8958_3_0"],"cc_8958_std_4":["jacket_M_sport5_h_std_cc_8958_2_0"],"cc_8958_std_5":["jacket_M_sport5_h_std_cc_8958_1_0"],"cc_8958_std_6":["jacket_M_sport5_h_std_cc_8958_0_0"],"cc_8958_std_7":["jacket_M_sport5_h_std_cc_8958_7_0"],"cc_8957_lay_2":["jacket_M_sport5_h_lay_cc_8957_2_0"],"cc_8957_lay_4":["jacket_M_sport5_h_lay_cc_8957_2_0"],"cc_8957_std_0":["jacket_M_sport5_h_std_cc_8957_0_0"],"cc_8957_std_1":["jacket_M_sport5_h_std_cc_8957_1_0"],"cc_8957_std_2":["jacket_M_sport5_h_std_cc_8957_2_0"],"cc_8957_std_3":["jacket_M_sport5_h_std_cc_8957_3_0"],"cc_8957_std_4":["jacket_M_sport5_h_std_cc_8957_2_0"],"cc_8957_std_5":["jacket_M_sport5_h_std_cc_8957_1_0"],"cc_8957_std_6":["jacket_M_sport5_h_std_cc_8957_0_0"],"cc_8957_std_7":["jacket_M_sport5_h_std_cc_8957_7_0"],"lc_8956_wav_0":["jacket_M_sport5_h_wav_lc_8956_0_0","jacket_M_sport5_h_wav_lc_8956_0_1"],"lc_8956_wav_1":["jacket_M_sport5_h_wav_lc_8956_1_0","jacket_M_sport5_h_wav_lc_8956_1_1"],"lc_8956_wav_2":["jacket_M_sport5_h_wav_lc_8956_2_0","jacket_M_sport5_h_wav_lc_8956_2_1"],"lc_8956_wav_3":["jacket_M_sport5_h_wav_lc_8956_3_0","jacket_M_sport5_h_wav_lc_8956_3_1"],"lc_8956_wav_4":["jacket_M_sport5_h_wav_lc_8956_4_0","jacket_M_sport5_h_wav_lc_8956_4_1"],"lc_8956_wav_5":["jacket_M_sport5_h_wav_lc_8956_5_0","jacket_M_sport5_h_wav_lc_8956_5_1"],"lc_8956_wav_6":["jacket_M_sport5_h_wav_lc_8956_6_0","jacket_M_sport5_h_wav_lc_8956_6_1"],"lc_8956_wav_7":["jacket_M_sport5_h_wav_lc_8956_7_0","jacket_M_sport5_h_wav_lc_8956_7_1"],"lc_8956_crr_0":["jacket_M_sport5_h_crr_lc_8956_0_0"],"lc_8956_crr_1":["jacket_M_sport5_h_crr_lc_8956_1_0"],"lc_8956_crr_2":["jacket_M_sport5_h_crr_lc_8956_2_0"],"lc_8956_crr_3":["jacket_M_sport5_h_crr_lc_8956_3_0"],"lc_8956_crr_4":["jacket_M_sport5_h_crr_lc_8956_2_0"],"lc_8956_crr_5":["jacket_M_sport5_h_crr_lc_8956_1_0"],"lc_8956_crr_6":["jacket_M_sport5_h_crr_lc_8956_0_0"],"lc_8956_crr_7":["jacket_M_sport5_h_crr_lc_8956_7_0"],"lc_8956_wlk_0":["jacket_M_sport5_h_wlk_lc_8956_0_0","jacket_M_sport5_h_wlk_lc_8956_0_1","jacket_M_sport5_h_wlk_lc_8956_0_2","jacket_M_sport5_h_wlk_lc_8956_0_3"],"lc_8956_wlk_1":["jacket_M_sport5_h_wlk_lc_8956_1_0","jacket_M_sport5_h_wlk_lc_8956_1_1","jacket_M_sport5_h_wlk_lc_8956_1_2","jacket_M_sport5_h_wlk_lc_8956_1_3"],"lc_8956_wlk_2":["jacket_M_sport5_h_wlk_lc_8956_2_0","jacket_M_sport5_h_wlk_lc_8956_2_1","jacket_M_sport5_h_wlk_lc_8956_2_2","jacket_M_sport5_h_wlk_lc_8956_2_3"],"lc_8956_wlk_3":["jacket_M_sport5_h_wlk_lc_8956_3_0","jacket_M_sport5_h_wlk_lc_8956_3_1","jacket_M_sport5_h_wlk_lc_8956_3_2","jacket_M_sport5_h_wlk_lc_8956_3_3"],"lc_8956_wlk_4":["jacket_M_sport5_h_wlk_lc_8956_2_0","jacket_M_sport5_h_wlk_lc_8956_2_1","jacket_M_sport5_h_wlk_lc_8956_2_2","jacket_M_sport5_h_wlk_lc_8956_2_3"],"lc_8956_wlk_5":["jacket_M_sport5_h_wlk_lc_8956_1_0","jacket_M_sport5_h_wlk_lc_8956_1_1","jacket_M_sport5_h_wlk_lc_8956_1_2","jacket_M_sport5_h_wlk_lc_8956_1_3"],"lc_8956_wlk_6":["jacket_M_sport5_h_wlk_lc_8956_0_0","jacket_M_sport5_h_wlk_lc_8956_0_1","jacket_M_sport5_h_wlk_lc_8956_0_2","jacket_M_sport5_h_wlk_lc_8956_0_3"],"lc_8956_wlk_7":["jacket_M_sport5_h_wlk_lc_8956_7_0","jacket_M_sport5_h_wlk_lc_8956_7_1","jacket_M_sport5_h_wlk_lc_8956_7_2","jacket_M_sport5_h_wlk_lc_8956_7_3"],"lc_8956_std_0":["jacket_M_sport5_h_std_lc_8956_0_0"],"lc_8956_std_1":["jacket_M_sport5_h_std_lc_8956_1_0"],"lc_8956_std_2":["jacket_M_sport5_h_std_lc_8956_2_0"],"lc_8956_std_3":["jacket_M_sport5_h_std_lc_8956_3_0"],"lc_8956_std_4":["jacket_M_sport5_h_std_lc_8956_2_0"],"lc_8956_std_5":["jacket_M_sport5_h_std_lc_8956_1_0"],"lc_8956_std_6":["jacket_M_sport5_h_std_lc_8956_0_0"],"lc_8956_std_7":["jacket_M_sport5_h_std_lc_8956_7_0"],"lc_8956_lay_2":["jacket_M_sport5_h_lay_lc_8956_2_0"],"lc_8956_lay_4":["jacket_M_sport5_h_lay_lc_8956_2_0"],"rc_8956_crr_0":["jacket_M_sport5_h_crr_rc_8956_0_0"],"rc_8956_crr_1":["jacket_M_sport5_h_crr_rc_8956_1_0"],"rc_8956_crr_2":["jacket_M_sport5_h_crr_rc_8956_2_0"],"rc_8956_crr_3":["jacket_M_sport5_h_crr_rc_8956_3_0"],"rc_8956_crr_4":["jacket_M_sport5_h_crr_rc_8956_2_0"],"rc_8956_crr_5":["jacket_M_sport5_h_crr_rc_8956_1_0"],"rc_8956_crr_6":["jacket_M_sport5_h_crr_rc_8956_0_0"],"rc_8956_crr_7":["jacket_M_sport5_h_crr_rc_8956_7_0"],"rc_8956_wlk_0":["jacket_M_sport5_h_wlk_rc_8956_0_0","jacket_M_sport5_h_wlk_rc_8956_0_1","jacket_M_sport5_h_wlk_rc_8956_0_2","jacket_M_sport5_h_wlk_rc_8956_0_3"],"rc_8956_wlk_1":["jacket_M_sport5_h_wlk_rc_8956_1_0","jacket_M_sport5_h_wlk_rc_8956_1_1","jacket_M_sport5_h_wlk_rc_8956_1_2","jacket_M_sport5_h_wlk_rc_8956_1_3"],"rc_8956_wlk_2":["jacket_M_sport5_h_wlk_rc_8956_2_0","jacket_M_sport5_h_wlk_rc_8956_2_1","jacket_M_sport5_h_wlk_rc_8956_2_2","jacket_M_sport5_h_wlk_rc_8956_2_3"],"rc_8956_wlk_3":["jacket_M_sport5_h_wlk_rc_8956_3_0","jacket_M_sport5_h_wlk_rc_8956_3_1","jacket_M_sport5_h_wlk_rc_8956_3_2","jacket_M_sport5_h_wlk_rc_8956_3_3"],"rc_8956_wlk_4":["jacket_M_sport5_h_wlk_rc_8956_2_0","jacket_M_sport5_h_wlk_rc_8956_2_1","jacket_M_sport5_h_wlk_rc_8956_2_2","jacket_M_sport5_h_wlk_rc_8956_2_3"],"rc_8956_wlk_5":["jacket_M_sport5_h_wlk_rc_8956_1_0","jacket_M_sport5_h_wlk_rc_8956_1_1","jacket_M_sport5_h_wlk_rc_8956_1_2","jacket_M_sport5_h_wlk_rc_8956_1_3"],"rc_8956_wlk_6":["jacket_M_sport5_h_wlk_rc_8956_0_0","jacket_M_sport5_h_wlk_rc_8956_0_1","jacket_M_sport5_h_wlk_rc_8956_0_2","jacket_M_sport5_h_wlk_rc_8956_0_3"],"rc_8956_wlk_7":["jacket_M_sport5_h_wlk_rc_8956_7_0","jacket_M_sport5_h_wlk_rc_8956_7_1","jacket_M_sport5_h_wlk_rc_8956_7_2","jacket_M_sport5_h_wlk_rc_8956_7_3"],"rc_8956_drk_0":["jacket_M_sport5_h_drk_rc_8956_0_0"],"rc_8956_drk_1":["jacket_M_sport5_h_drk_rc_8956_1_0"],"rc_8956_drk_2":["jacket_M_sport5_h_drk_rc_8956_2_0"],"rc_8956_drk_3":["jacket_M_sport5_h_drk_rc_8956_3_0"],"rc_8956_drk_4":["jacket_M_sport5_h_drk_rc_8956_4_0"],"rc_8956_drk_5":["jacket_M_sport5_h_drk_rc_8956_5_0"],"rc_8956_drk_6":["jacket_M_sport5_h_drk_rc_8956_6_0"],"rc_8956_drk_7":["jacket_M_sport5_h_drk_rc_8956_7_0"],"rc_8956_lay_2":["jacket_M_sport5_h_lay_rc_8956_2_0"],"rc_8956_lay_4":["jacket_M_sport5_h_lay_rc_8956_2_0"],"rc_8956_std_0":["jacket_M_sport5_h_std_rc_8956_0_0"],"rc_8956_std_1":["jacket_M_sport5_h_std_rc_8956_1_0"],"rc_8956_std_2":["jacket_M_sport5_h_std_rc_8956_2_0"],"rc_8956_std_3":["jacket_M_sport5_h_std_rc_8956_3_0"],"rc_8956_std_4":["jacket_M_sport5_h_std_rc_8956_2_0"],"rc_8956_std_5":["jacket_M_sport5_h_std_rc_8956_1_0"],"rc_8956_std_6":["jacket_M_sport5_h_std_rc_8956_0_0"],"rc_8956_std_7":["jacket_M_sport5_h_std_rc_8956_7_0"]},"partsType":{"cc":{"gestures":["lay","std"]},"lc":{"gestures":["wav","crr","wlk","std","lay"]},"rc":{"gestures":["crr","wlk","drk","lay","std"]}}}